pmgwidgets/__init__.py
pmgwidgets/get_time_consuming_classes.py
pmgwidgets/display/__init__.py
pmgwidgets/display/examples.py
pmgwidgets/display/browser/__init__.py
pmgwidgets/display/browser/browser.py
pmgwidgets/display/browser/get_ipy.py
pmgwidgets/display/browser/handler.py
pmgwidgets/display/dynamicgraph/__init__.py
pmgwidgets/display/dynamicgraph/pgexample.py
pmgwidgets/display/dynamicgraph/base/__init__.py
pmgwidgets/display/dynamicgraph/base/basetimeseries.py
pmgwidgets/display/dynamicgraph/mplplots/__init__.py
pmgwidgets/display/dynamicgraph/pgplots/__init__.py
pmgwidgets/display/matplotlib/__init__.py
pmgwidgets/display/matplotlib/pmagg.py
pmgwidgets/display/matplotlib/qt5agg.py
pmgwidgets/display/matplotlib/pyqtgraph/__init__.py
pmgwidgets/display/matplotlib/pyqtgraph/pyqtgraphwidget.py
pmgwidgets/display/vtk/__init__.py
pmgwidgets/doc_figures/nested_lists_to_place_widgets.png
pmgwidgets/doc_figures/pmflowarea_1.png
pmgwidgets/doc_figures/pmflowarea_2.png
pmgwidgets/doc_figures/settings_panel.png
pmgwidgets/docs/threading_and_tasking.md
pmgwidgets/docs/doc_figures/pmflowarea_2.png
pmgwidgets/elements/__init__.py
pmgwidgets/elements/dockobject.py
pmgwidgets/elements/toolbar.py
pmgwidgets/examples/__init__.py
pmgwidgets/examples/utilities/__init__.py
pmgwidgets/examples/utilities/examples.py
pmgwidgets/examples/utilities/long_conn.py
pmgwidgets/flowchart/__init__.py
pmgwidgets/flowchart/create_node_content_class.md
pmgwidgets/flowchart/dataprocesswidget.py
pmgwidgets/flowchart/readme.md
pmgwidgets/flowchart/readme_arch.md
pmgwidgets/flowchart/simulationwidget.py
pmgwidgets/flowchart/创建新节点(deprecated).md
pmgwidgets/flowchart/core/__init__.py
pmgwidgets/flowchart/core/flow_content.py
pmgwidgets/flowchart/core/flow_items.py
pmgwidgets/flowchart/core/flow_node.py
pmgwidgets/flowchart/core/flowchart_scene.py
pmgwidgets/flowchart/core/flowchart_widget.py
pmgwidgets/flowchart/core/nodemanager.py
pmgwidgets/flowchart/core/utils.py
pmgwidgets-0.9.4.dist-info/LICENSE
pmgwidgets-0.9.4.dist-info/METADATA
pmgwidgets-0.9.4.dist-info/WHEEL
pmgwidgets-0.9.4.dist-info/top_level.txt
pmgwidgets-0.9.4.dist-info/RECORD
